flake8_super_call.py
flake8_super_call-1.0.0.dist-info/METADATA
flake8_super_call-1.0.0.dist-info/RECORD
flake8_super_call-1.0.0.dist-info/WHEEL
flake8_super_call-1.0.0.dist-info/entry_points.txt
flake8_super_call-1.0.0.dist-info/top_level.txt
flake8_super_call-1.0.0.dist-info/zip-safe
