Metadata-Version: 2.1
Name: flake8-super-call
Version: 1.0.0
Summary: flake8 super call checker
Home-page: https://github.com/DragosOprica/flake8-super-call
Author: Dragos Oprica
Author-email: dragos.oprica92@gmail.com
License: MIT
Download-URL: https://github.com/DragosOprica/flake8-super-call/tarball/1.0.0
Keywords: flake8 super
Platform: UNKNOWN
Classifier: Environment :: Console
Classifier: Framework :: Flake8
Classifier: Intended Audience :: Developers
Classifier: License :: OSI Approved :: MIT License
Classifier: Programming Language :: Python
Classifier: Programming Language :: Python :: 2
Classifier: Programming Language :: Python :: 3
Classifier: Topic :: Software Development :: Libraries :: Python Modules
Classifier: Topic :: Software Development :: Quality Assurance
Requires-Dist: flake8 (>=3.0.0)
